phrenktest/__init__.py
phrenktest/hello.py
phrenktest/__pycache__/__init__.cpython-39.pyc
phrenktest/__pycache__/hello.cpython-39.pyc
phrenktest/othermodule/__init__.py
phrenktest/othermodule/hello2.py
phrenktest-0.1.3.data/data/requirements.txt
phrenktest-0.1.3.dist-info/METADATA
phrenktest-0.1.3.dist-info/WHEEL
phrenktest-0.1.3.dist-info/top_level.txt
phrenktest-0.1.3.dist-info/RECORD
