Metadata-Version: 2.1
Name: phrenktest
Version: 0.1.3
Summary: testest
Author: test
